aiogtts/__init__.py
aiogtts/lang.py
aiogtts/langs.py
aiogtts/tts.py
aiogtts/utils.py
aiogtts/tokenizer/__init__.py
aiogtts/tokenizer/core.py
aiogtts/tokenizer/pre_processors.py
aiogtts/tokenizer/symbols.py
aiogtts/tokenizer/tokenizer_cases.py
aiogTTS-1.1.1.dist-info/LICENSE
aiogTTS-1.1.1.dist-info/METADATA
aiogTTS-1.1.1.dist-info/WHEEL
aiogTTS-1.1.1.dist-info/top_level.txt
aiogTTS-1.1.1.dist-info/RECORD
