Metadata-Version: 2.1
Name: aiogTTS
Version: 1.1.1
Summary: A Python library to interface with Google Translate text-to-speech API
Home-page: https://github.com/Helow19274/aiogTTS
Author: Helow19274
Author-email: helow@helow19274.tk
License: UNKNOWN
Platform: UNKNOWN
Classifier: License :: OSI Approved :: MIT License
Classifier: Operating System :: OS Independent
Classifier: Programming Language :: Python :: 3.6
Classifier: Programming Language :: Python :: 3.7
Classifier: Programming Language :: Python :: 3.8
Classifier: Programming Language :: Python :: 3.9
Classifier: Programming Language :: Python :: 3.10
Classifier: Programming Language :: Python :: Implementation :: CPython
Classifier: Topic :: Software Development :: Libraries
Classifier: Topic :: Multimedia :: Sound/Audio :: Speech
License-File: LICENSE
Requires-Dist: aiohttp
Requires-Dist: beautifulsoup4
Provides-Extra: tests
Requires-Dist: pytest-asyncio ; extra == 'tests'
